asyncom/__init__.py
asyncom/om.py
asyncom/utils.py
asyncom-0.2.3.dist-info/AUTHORS.rst
asyncom-0.2.3.dist-info/LICENSE
asyncom-0.2.3.dist-info/METADATA
asyncom-0.2.3.dist-info/WHEEL
asyncom-0.2.3.dist-info/top_level.txt
asyncom-0.2.3.dist-info/RECORD
