Metadata-Version: 2.1
Name: asyncom
Version: 0.2.3
Summary: Small and partial Obejct mapper on top of sqlalchemy for async
Home-page: https://github.com/vinissimus/asyncom
Author: Jordi Collell
Author-email: jordic@gmail.com
License: MIT license
Keywords: asyncom
Platform: UNKNOWN
Classifier: Development Status :: 2 - Pre-Alpha
Classifier: Intended Audience :: Developers
Classifier: License :: OSI Approved :: MIT License
Classifier: Natural Language :: English
Classifier: Programming Language :: Python :: 3.6
Classifier: Programming Language :: Python :: 3.7
Requires-Dist: sqlalchemy
Requires-Dist: asyncpg
Requires-Dist: databases
